Qarvexium/__init__.py
Qarvexium/module.py
qarvexium-0.1.9.dist-info/licenses/LICENSE
qarvexium-0.1.9.dist-info/METADATA
qarvexium-0.1.9.dist-info/WHEEL
qarvexium-0.1.9.dist-info/top_level.txt
qarvexium-0.1.9.dist-info/RECORD
