Metadata-Version: 2.4
Name: Qarvexium
Version: 0.1.9
Summary: Qarvexium Python Module One Step Ahead
Author-email: Qarvexium <Qarvexium@proton.me>
License: Qarvexium Software Agreement
Project-URL: Homepage, https://pypi.org/project/Qarvexium/
Keywords: Qarvexium,QOL,Quality of life,Easier Python,easy python
Classifier: Programming Language :: Python :: 3
Classifier: Intended Audience :: Developers
Classifier: Operating System :: Microsoft :: Windows
Requires-Python: >=3.9
License-File: LICENSE
Dynamic: license-file
